setup.py
tmg/__init__.py
tmg/dynamics.py
tmg/preprocess.py
tmg.egg-info/PKG-INFO
tmg.egg-info/SOURCES.txt
tmg.egg-info/dependency_links.txt
tmg.egg-info/not-zip-safe
tmg.egg-info/top_level.txt