Metadata-Version: 1.0
Name: tmg
Version: 0.3
Summary: Topic Modelling Games
Home-page: http://github.com/roccotrip/tmg
Author: Rocco Tripodi
Author-email: rocco.tripodi@gmail.com
License: MIT
Platform: UNKNOWN
